netpyne/__init__.py
netpyne/analysis.py
netpyne/batch.py
netpyne/cell.py
netpyne/network.py
netpyne/neuromlFuncs.py
netpyne/pop.py
netpyne/sim.py
netpyne/simFuncs.py
netpyne/specs.py
netpyne/utils.py
netpyne/wrappers.py
netpyne/metadata/__init__.py
netpyne/metadata/api.py
netpyne/metadata/metadata.py
netpyne/support/__init__.py
netpyne/support/bsmart.py
netpyne/support/morphology.py
netpyne/support/recxelectrode.py
netpyne/support/scalebar.py
netpyne/support/stackedBarGraph.py
netpyne/tests/__init__.py
netpyne/tests/tests.py
netpyne/tests/validate_tests.py
netpyne_py3-0.7.9.dist-info/METADATA
netpyne_py3-0.7.9.dist-info/RECORD
netpyne_py3-0.7.9.dist-info/WHEEL
netpyne_py3-0.7.9.dist-info/top_level.txt
