Metadata-Version: 2.1
Name: netpyne-py3
Version: 0.7.9
Summary: A Python package to develop, simulate and analyse biological neuronal networks in NEURON.
Home-page: https://github.com/Neurosim-lab/netpyne
Author: Salvador Dura-Bernal (Neurosim lab)
Author-email: salvadordura@gmail.com
License: MIT
Keywords: neuron,network,developing,framework,biological,simulation
Platform: UNKNOWN
Classifier: Development Status :: 4 - Beta
Classifier: Intended Audience :: Science/Research
Classifier: Topic :: Scientific/Engineering :: Visualization
Classifier: License :: OSI Approved :: MIT License
Classifier: Programming Language :: Python :: 3
Classifier: Programming Language :: Python :: 3.6
Classifier: Programming Language :: Python :: 3.7
Requires-Python: >3.6
Requires-Dist: numpy
Requires-Dist: scipy
Requires-Dist: matplotlib
